[
  {
    "cuenta": "Jose@correo.com",
    "nombre": "Jose Luis",
    "nombreCompleto": "José Luis Narváez Martínez",
    "examen": false,
    "comprado": false,
    "contrasena": "Jose123"
  },
  {
    "cuenta": "Harim@correo.com",
    "nombre": "Harim Jesus",
    "nombreCompleto": "Harim Jesús Enrique Dueñas Dávila",
    "examen": false,
    "comprado": false,
    "contrasena": "Harim123"
  },
  {
    "cuenta": "Julian@correo.com",
    "nombre": "Julian Emmanuel",
    "nombreCompleto": "Julián Emmanuel Hernández",
    "examen": false,
    "comprado": false,
    "contrasena": "Julian123"
  },
  {
    "cuenta": "Santos@correo.com",
    "nombre": "Emiliano Santos",
    "nombreCompleto": "Emiliano Alejandro Santos González",
    "examen": false,
    "comprado": false,
    "contrasena": "Santos123"
  },
  {
    "cuenta": "Georgina@correo.com",
    "nombre": "Mtra. Georgina",
    "examen": false,
    "comprado": false,
    "contrasena": "dieLehrerin"
  },
  {
    "cuenta": "Guido@correo.com",
    "nombre": "SuperGuido",
    "examen": false,
    "comprado": false,
    "contrasena": "PasenLista"
  }
]